odoo10_addon_purchase_fop_shipping-10.0.1.0.0.99.dev17-py3.8-nspkg.pth
odoo/addons/purchase_fop_shipping/README.rst
odoo/addons/purchase_fop_shipping/__init__.py
odoo/addons/purchase_fop_shipping/__manifest__.py
odoo/addons/purchase_fop_shipping/i18n/de.po
odoo/addons/purchase_fop_shipping/i18n/es.po
odoo/addons/purchase_fop_shipping/i18n/es_PE.po
odoo/addons/purchase_fop_shipping/i18n/fr.po
odoo/addons/purchase_fop_shipping/i18n/fr_BE.po
odoo/addons/purchase_fop_shipping/i18n/gl.po
odoo/addons/purchase_fop_shipping/i18n/hr.po
odoo/addons/purchase_fop_shipping/i18n/it.po
odoo/addons/purchase_fop_shipping/i18n/nl.po
odoo/addons/purchase_fop_shipping/i18n/nl_NL.po
odoo/addons/purchase_fop_shipping/i18n/pt_BR.po
odoo/addons/purchase_fop_shipping/i18n/purchase_fop_shipping.pot
odoo/addons/purchase_fop_shipping/i18n/ro.po
odoo/addons/purchase_fop_shipping/i18n/sl.po
odoo/addons/purchase_fop_shipping/i18n/vi_VN.po
odoo/addons/purchase_fop_shipping/models/__init__.py
odoo/addons/purchase_fop_shipping/models/partner.py
odoo/addons/purchase_fop_shipping/models/purchase.py
odoo/addons/purchase_fop_shipping/security/purchase_group.xml
odoo/addons/purchase_fop_shipping/static/description/icon.png
odoo/addons/purchase_fop_shipping/tests/__init__.py
odoo/addons/purchase_fop_shipping/tests/test_fop_shipping.py
odoo/addons/purchase_fop_shipping/views/partner_view.xml
odoo/addons/purchase_fop_shipping/views/purchase_view.xml
odoo10_addon_purchase_fop_shipping-10.0.1.0.0.99.dev17.dist-info/METADATA
odoo10_addon_purchase_fop_shipping-10.0.1.0.0.99.dev17.dist-info/WHEEL
odoo10_addon_purchase_fop_shipping-10.0.1.0.0.99.dev17.dist-info/namespace_packages.txt
odoo10_addon_purchase_fop_shipping-10.0.1.0.0.99.dev17.dist-info/top_level.txt
odoo10_addon_purchase_fop_shipping-10.0.1.0.0.99.dev17.dist-info/RECORD
